konfigleser/README.MD
konfigleser/__init__.py
konfigleser/requirements.txt
konfigleser/thirdparty.json
konfigleser-0.10.dist-info/LICENSE.rst
konfigleser-0.10.dist-info/METADATA
konfigleser-0.10.dist-info/WHEEL
konfigleser-0.10.dist-info/top_level.txt
konfigleser-0.10.dist-info/RECORD
