Metadata-Version: 2.1
Name: konfigleser
Version: 0.10
Summary: parses config files and converts the data types
Home-page: https://github.com/hansalemaos/konfigleser
Author: Johannes Fischer
Author-email: aulasparticularesdealemaosp@gmail.com
License: MIT
Keywords: config,parser
Classifier: Development Status :: 4 - Beta
Classifier: Programming Language :: Python :: 3 :: Only
Classifier: Programming Language :: Python :: 3.10
Classifier: Topic :: Software Development :: Libraries :: Python Modules
Classifier: Topic :: Utilities
License-File: LICENSE.rst
Requires-Dist: flatten-any-dict-iterable-or-whatsoever
Requires-Dist: mymulti-key-dict
Requires-Dist: touchtouch
